[{"word":"aircraft","f1":0.000457,"f2":-0.257498,"regime":"turbulent","peak":1972,"ncp":3},{"word":"army","f1":0.165951,"f2":0.085401,"regime":"stable","peak":1815,"ncp":3},{"word":"automobile","f1":-0.075956,"f2":-0.206829,"regime":"turbulent","peak":1929,"ncp":2},{"word":"battle","f1":0.167116,"f2":0.079875,"regime":"stable","peak":1863,"ncp":4},{"word":"biology","f1":-0.176413,"f2":0.030784,"regime":"adoption","peak":2008,"ncp":4},{"word":"capitalism","f1":-0.034065,"f2":-0.237744,"regime":"turbulent","peak":2008,"ncp":3},{"word":"chemistry","f1":-0.173211,"f2":0.058189,"regime":"stable","peak":1969,"ncp":6},{"word":"cinema","f1":0.03039,"f2":-0.200309,"regime":"turbulent","peak":2008,"ncp":2},{"word":"communism","f1":-0.17509,"f2":0.030876,"regime":"turbulent","peak":1962,"ncp":3},{"word":"computer","f1":0.054208,"f2":-0.074935,"regime":"turbulent","peak":1987,"ncp":5},{"word":"crisis","f1":0.172434,"f2":0.032338,"regime":"stable","peak":1974,"ncp":6},{"word":"culture","f1":0.15274,"f2":0.117309,"regime":"stable","peak":2008,"ncp":5},{"word":"democracy","f1":0.144774,"f2":-0.154306,"regime":"stable","peak":1941,"ncp":7},{"word":"disease","f1":0.004508,"f2":0.252924,"regime":"stable","peak":2008,"ncp":9},{"word":"economy","f1":0.056989,"f2":-0.017927,"regime":"stable","peak":1992,"ncp":6},{"word":"education","f1":-0.085779,"f2":-0.177256,"regime":"stable","peak":1971,"ncp":5},{"word":"election","f1":0.096097,"f2":-0.027724,"regime":"stable","peak":1801,"ncp":5},{"word":"electricity","f1":-0.163519,"f2":0.094075,"regime":"stable","peak":1892,"ncp":7},{"word":"empire","f1":0.167516,"f2":0.075938,"regime":"decline","peak":1812,"ncp":4},{"word":"evolution","f1":-0.163295,"f2":0.074161,"regime":"stable","peak":2008,"ncp":4},{"word":"factory","f1":-0.119117,"f2":-0.082965,"regime":"decline","peak":1920,"ncp":7},{"word":"freedom","f1":0.168733,"f2":-0.050915,"regime":"stable","peak":1848,"ncp":7},{"word":"government","f1":0.172451,"f2":-0.067351,"regime":"stable","peak":1815,"ncp":6},{"word":"industry","f1":-0.086896,"f2":-0.080608,"regime":"stable","peak":1945,"ncp":6},{"word":"internet","f1":0.167049,"f2":0.013643,"regime":"turbulent","peak":2008,"ncp":5},{"word":"justice","f1":0.129047,"f2":0.161927,"regime":"decline","peak":1819,"ncp":4},{"word":"king","f1":0.164622,"f2":0.099844,"regime":"decline","peak":1810,"ncp":4},{"word":"labour","f1":0.172796,"f2":-0.03959,"regime":"decline","peak":1821,"ncp":5},{"word":"literature","f1":-0.159668,"f2":0.116682,"regime":"stable","peak":1979,"ncp":3},{"word":"marriage","f1":0.175314,"f2":0.008405,"regime":"stable","peak":1800,"ncp":5},{"word":"medicine","f1":0.158073,"f2":0.081515,"regime":"stable","peak":1886,"ncp":8},{"word":"nationalism","f1":-0.169417,"f2":-0.076996,"regime":"turbulent","peak":2008,"ncp":4},{"word":"newspaper","f1":-0.164385,"f2":0.090785,"regime":"stable","peak":1947,"ncp":5},{"word":"nuclear","f1":-0.055766,"f2":-0.225187,"regime":"turbulent","peak":1982,"ncp":4},{"word":"parliament","f1":0.175682,"f2":-0.048225,"regime":"turbulent","peak":1810,"ncp":5},{"word":"peace","f1":0.174176,"f2":-0.062572,"regime":"stable","peak":1815,"ncp":4},{"word":"philosophy","f1":0.056654,"f2":0.181595,"regime":"stable","peak":1841,"ncp":10},{"word":"photography","f1":-0.061992,"f2":-0.075614,"regime":"stable","peak":1978,"ncp":6},{"word":"physics","f1":-0.175037,"f2":0.044642,"regime":"stable","peak":1966,"ncp":4},{"word":"poverty","f1":0.178397,"f2":-0.001436,"regime":"stable","peak":1967,"ncp":6},{"word":"radio","f1":-0.016047,"f2":-0.232318,"regime":"turbulent","peak":1946,"ncp":2},{"word":"religion","f1":0.174351,"f2":0.043278,"regime":"stable","peak":1801,"ncp":5},{"word":"revolution","f1":0.171269,"f2":-0.054939,"regime":"stable","peak":1818,"ncp":5},{"word":"satellite","f1":0.03245,"f2":0.114908,"regime":"turbulent","peak":1987,"ncp":7},{"word":"science","f1":0.001524,"f2":0.239511,"regime":"stable","peak":1850,"ncp":8},{"word":"society","f1":0.027368,"f2":0.176282,"regime":"stable","peak":1820,"ncp":7},{"word":"soldier","f1":-0.03579,"f2":0.246984,"regime":"stable","peak":1864,"ncp":6},{"word":"surgery","f1":-0.024658,"f2":0.26048,"regime":"stable","peak":2008,"ncp":5},{"word":"telegraph","f1":-0.078947,"f2":-0.009519,"regime":"decline","peak":1882,"ncp":6},{"word":"telephone","f1":-0.05323,"f2":-0.18038,"regime":"turbulent","peak":1918,"ncp":4},{"word":"television","f1":0.03259,"f2":-0.1859,"regime":"turbulent","peak":1963,"ncp":5},{"word":"terror","f1":0.156814,"f2":0.070122,"regime":"stable","peak":1800,"ncp":4},{"word":"theory","f1":-0.142961,"f2":0.137453,"regime":"stable","peak":1967,"ncp":4},{"word":"trade","f1":-0.173335,"f2":0.056322,"regime":"stable","peak":1921,"ncp":10},{"word":"vaccine","f1":0.144679,"f2":-0.152485,"regime":"stable","peak":2008,"ncp":5},{"word":"war","f1":0.128169,"f2":0.043438,"regime":"stable","peak":1943,"ncp":8},{"word":"weapon","f1":0.167728,"f2":-0.045431,"regime":"stable","peak":2008,"ncp":5},{"word":"wireless","f1":-0.001173,"f2":-0.114714,"regime":"turbulent","peak":2008,"ncp":5}]